{
  "meta": {
    "scanned_at_bj": "2026-03-09T09:46:23.109Z",
    "session": "AM",
    "trend_summary": {
      "VIRAL_UNCATEGORIZED": 14,
      "CODE_LEVERAGE": 3,
      "TALENT_GROWTH": 2,
      "CORE_PRAGMATISM": 1,
      "KNOWLEDGE_BASE": 1
    }
  },
  "items": [
    {
      "name": "HKUDS/CLI-Anything",
      "stars": 163,
      "tags": [
        "CODE_LEVERAGE"
      ],
      "reason": "STRATEGY",
      "url": "https://github.com/HKUDS/CLI-Anything"
    },
    {
      "name": "trevin-creator/autoresearch-mlx",
      "stars": 155,
      "tags": [
        "CODE_LEVERAGE",
        "TALENT_GROWTH"
      ],
      "reason": "STRATEGY",
      "url": "https://github.com/trevin-creator/autoresearch-mlx"
    },
    {
      "name": "ammaarreshi/SkyRoads-Codex",
      "stars": 116,
      "tags": [
        "CORE_PRAGMATISM"
      ],
      "reason": "STRATEGY",
      "url": "https://github.com/ammaarreshi/SkyRoads-Codex"
    },
    {
      "name": "nagisanzenin/skyclaw",
      "stars": 76,
      "tags": [
        "CODE_LEVERAGE"
      ],
      "reason": "STRATEGY",
      "url": "https://github.com/nagisanzenin/skyclaw"
    }
  ]
}